mcp_feedback_collector/__init__.py
mcp_feedback_collector/server.py
mcp_feedback_collector-2.0.0.dist-info/METADATA
mcp_feedback_collector-2.0.0.dist-info/WHEEL
mcp_feedback_collector-2.0.0.dist-info/entry_points.txt
mcp_feedback_collector-2.0.0.dist-info/licenses/LICENSE
mcp_feedback_collector-2.0.0.dist-info/RECORD
